{
  "thoughts": [
    {
      "id": 1,
      "content": "Que bom que você veio!",
      "authorship": "Bruno",
      "model": "modelo2"
    },
    {
      "id": 2,
      "content": "Eu quero vingança!",
      "authorship": "Bruno",
      "model": "modelo3"
    },
    {
      "id": 3,
      "content": "Eu amo tecnologia!",
      "authorship": "Bruno",
      "model": "modelo3"
    },
    {
      "content": "Mais vale um pássaro na mão que dois voando.",
      "authorship": "Ditos populares",
      "model": "modelo1",
      "id": 4
    },
    {
      "content": "Que a força esteja com você!",
      "authorship": "Mestre Yoda",
      "model": "modelo2",
      "id": 5
    },
    {
      "content": "Emacipate yourself from mental slavery",
      "authorship": "Bob Marley",
      "model": "modelo3",
      "id": 6
    },
    {
      "content": "Em terra de cego, quem tem olho é rei.",
      "authorship": "Provérbios populares",
      "model": "modelo2",
      "id": 7
    }
  ]
}